gradientlab/__init__.py
gradientlab/data_utils/experiment_path.py
gradientlab/data_utils/text_ds_packing.py
gradientlab/data_utils/torch_datasets/tokenized_text_ds.py
gradientlab/experiments/exp20251016_0_lm_20m_polyrelu_lm_vanilla_fineweb_ita/README.md
gradientlab/experiments/exp20251016_0_lm_20m_polyrelu_lm_vanilla_fineweb_ita/RESULTS.md
gradientlab/experiments/exp20251016_0_lm_20m_polyrelu_lm_vanilla_fineweb_ita/__main__.py
gradientlab/experiments/exp20251016_0_lm_20m_polyrelu_lm_vanilla_fineweb_ita/dataprep.py
gradientlab/experiments/exp20251016_0_lm_20m_polyrelu_lm_vanilla_fineweb_ita/eval.py
gradientlab/experiments/exp20251016_0_lm_20m_polyrelu_lm_vanilla_fineweb_ita/exp_config.py
gradientlab/experiments/exp20251016_0_lm_20m_polyrelu_lm_vanilla_fineweb_ita/modeling/attention.py
gradientlab/experiments/exp20251016_0_lm_20m_polyrelu_lm_vanilla_fineweb_ita/modeling/factory.py
gradientlab/experiments/exp20251016_0_lm_20m_polyrelu_lm_vanilla_fineweb_ita/modeling/model.py
gradientlab/experiments/exp20251016_0_lm_20m_polyrelu_lm_vanilla_fineweb_ita/modeling/model_cfg.py
gradientlab/experiments/exp20251016_0_lm_20m_polyrelu_lm_vanilla_fineweb_ita/modeling/positional_encoding.py
gradientlab/experiments/exp20251016_0_lm_20m_polyrelu_lm_vanilla_fineweb_ita/modeling/transformer.py
gradientlab/experiments/exp20251016_0_lm_20m_polyrelu_lm_vanilla_fineweb_ita/trainer.py
gradientlab/experiments/exp20251025_0_vlm_20m_in1k/README.md
gradientlab/experiments/exp20251025_0_vlm_20m_in1k/RESULTS.md
gradientlab/experiments/exp20251025_0_vlm_20m_in1k/__main__.py
gradientlab/experiments/exp20251025_0_vlm_20m_in1k/dataprep.py
gradientlab/experiments/exp20251025_0_vlm_20m_in1k/dataprep_download.py
gradientlab/experiments/exp20251025_0_vlm_20m_in1k/eval.py
gradientlab/experiments/exp20251025_0_vlm_20m_in1k/exp_config.py
gradientlab/experiments/exp20251025_0_vlm_20m_in1k/modeling/attention.py
gradientlab/experiments/exp20251025_0_vlm_20m_in1k/modeling/factory.py
gradientlab-0.1.3.dist-info/WHEEL
gradientlab-0.1.3.dist-info/METADATA
gradientlab-0.1.3.dist-info/RECORD
