Metadata-Version: 2.3
Name: gradientlab
Version: 0.1.3
Summary: A lab where gradients flow and models go to prod.
Author: Mauro Sciancalepore
Author-email: Mauro Sciancalepore <maurosciancalepore98@gmail.com>
Requires-Dist: accelerate>=1.10.1
Requires-Dist: datasets>=4.2.0
Requires-Dist: ipykernel>=7.0.1
Requires-Dist: matplotlib>=3.10.7
Requires-Dist: pydantic<2.12
Requires-Dist: setuptools>=80.9.0
Requires-Dist: torch>=2.9.0
Requires-Dist: torchvision>=0.24.0
Requires-Dist: trackio>=0.6.0
Requires-Dist: transformers>=4.57.1
Requires-Python: >=3.10
